{"directed": false, "multigraph": false, "graph": {}, "nodes": [{"id": 0}, {"id": -1}, {"id": 1}, {"id": 2}, {"id": -3}, {"id": 3}, {"id": 4}, {"id": -5}, {"id": 5}, {"id": 6}, {"id": -7}, {"id": 7}, {"id": 8}, {"id": -9}, {"id": 9}, {"id": 10}, {"id": -11}, {"id": 11}, {"id": 12}, {"id": -13}, {"id": 13}, {"id": 14}, {"id": -15}, {"id": 15}, {"id": 16}, {"id": -17}, {"id": 17}, {"id": 18}, {"id": -19}, {"id": 19}, {"id": 20}, {"id": -21}, {"id": 21}, {"id": 22}, {"id": -23}, {"id": 23}, {"id": 24}, {"id": -25}, {"id": 25}, {"id": 26}, {"id": -27}, {"id": 27}, {"id": 28}, {"id": -29}, {"id": 29}, {"id": 30}, {"id": -31}, {"id": 31}, {"id": -33}, {"id": -34}, {"id": -37}, {"id": -38}, {"id": -41}, {"id": -42}, {"id": -45}, {"id": -46}, {"id": -49}, {"id": -50}, {"id": -53}, {"id": -54}, {"id": -57}, {"id": -58}, {"id": -61}, {"id": -62}, {"id": -65}, {"id": -67}, {"id": -69}, {"id": -71}, {"id": -73}, {"id": -75}, {"id": -77}, {"id": -79}, {"id": -81}, {"id": -83}, {"id": -85}, {"id": -87}, {"id": -89}, {"id": -91}, {"id": -93}, {"id": -95}, {"id": -97}, {"id": -98}, {"id": -99}, {"id": -100}, {"id": -105}, {"id": -106}, {"id": -107}, {"id": -108}, {"id": -113}, {"id": -114}, {"id": -115}, {"id": -116}, {"id": -121}, {"id": -122}, {"id": -123}, {"id": -124}, {"id": -129}, {"id": -131}, {"id": -133}, {"id": -135}, {"id": -137}, {"id": -139}, {"id": -141}, {"id": -143}, {"id": -145}, {"id": -147}, {"id": -149}, {"id": -151}, {"id": -153}, {"id": -155}, {"id": -157}, {"id": -159}, {"id": -161}, {"id": -162}, {"id": -165}, {"id": -166}, {"id": -169}, {"id": -170}, {"id": -173}, {"id": -174}, {"id": -177}, {"id": -178}, {"id": -181}, {"id": -182}, {"id": -185}, {"id": -186}, {"id": -189}, {"id": -190}, {"id": -193}, {"id": -195}, {"id": -197}, {"id": -199}, {"id": -201}, {"id": -203}, {"id": -205}, {"id": -207}, {"id": -209}, {"id": -211}, {"id": -213}, {"id": -215}, {"id": -217}, {"id": -219}, {"id": -221}, {"id": -223}, {"id": -225}, {"id": -226}, {"id": -227}, {"id": -228}, {"id": -229}, {"id": -230}, {"id": -231}, {"id": -232}, {"id": -241}, {"id": -242}, {"id": -243}, {"id": -244}, {"id": -245}, {"id": -246}, {"id": -247}, {"id": -248}, {"id": -257}, {"id": -259}, {"id": -261}, {"id": -263}, {"id": -265}, {"id": -267}, {"id": -269}, {"id": -271}, {"id": -273}, {"id": -275}, {"id": -277}, {"id": -279}, {"id": -281}, {"id": -283}, {"id": -285}, {"id": -287}, {"id": -289}, {"id": -290}, {"id": -293}, {"id": -294}, {"id": -297}, {"id": -298}, {"id": -301}, {"id": -302}, {"id": -305}, {"id": -306}, {"id": -309}, {"id": -310}, {"id": -313}, {"id": -314}, {"id": -317}, {"id": -318}, {"id": -321}, {"id": -323}, {"id": -325}, {"id": -327}, {"id": -329}, {"id": -331}, {"id": -333}, {"id": -335}, {"id": -337}, {"id": -339}, {"id": -341}, {"id": -343}, {"id": -345}, {"id": -347}, {"id": -349}, {"id": -351}, {"id": -353}, {"id": -354}, {"id": -355}, {"id": -356}, {"id": -361}, {"id": -362}, {"id": -363}, {"id": -364}, {"id": -369}, {"id": -370}, {"id": -371}, {"id": -372}, {"id": -377}, {"id": -378}, {"id": -379}, {"id": -380}, {"id": -385}, {"id": -387}, {"id": -389}, {"id": -391}, {"id": -393}, {"id": -395}, {"id": -397}, {"id": -399}, {"id": -401}, {"id": -403}, {"id": -405}, {"id": -407}, {"id": -409}, {"id": -411}, {"id": -413}, {"id": -415}, {"id": -417}, {"id": -418}, {"id": -421}, {"id": -422}, {"id": -425}, {"id": -426}, {"id": -429}, {"id": -430}, {"id": -433}, {"id": -434}, {"id": -437}, {"id": -438}, {"id": -441}, {"id": -442}, {"id": -445}, {"id": -446}, {"id": -449}, {"id": -451}, {"id": -453}, {"id": -455}, {"id": -457}, {"id": -459}, {"id": -461}, {"id": -463}, {"id": -465}, {"id": -467}, {"id": -469}, {"id": -471}, {"id": -473}, {"id": -475}, {"id": -477}, {"id": -479}, {"id": -481}, {"id": -482}, {"id": -483}, {"id": -484}, {"id": -485}, {"id": -486}, {"id": -487}, {"id": -488}, {"id": -489}, {"id": -490}, {"id": -491}, {"id": -492}, {"id": -493}, {"id": -494}, {"id": -495}, {"id": -496}, {"id": -513}, {"id": -515}, {"id": -517}, {"id": -519}, {"id": -521}, {"id": -523}, {"id": -525}, {"id": -527}, {"id": -529}, {"id": -531}, {"id": -533}, {"id": -535}, {"id": -537}, {"id": -539}, {"id": -541}, {"id": -543}, {"id": -545}, {"id": -546}, {"id": -549}, {"id": -550}, {"id": -553}, {"id": -554}, {"id": -557}, {"id": -558}, {"id": -561}, {"id": -562}, {"id": -565}, {"id": -566}, {"id": -569}, {"id": -570}, {"id": -573}, {"id": -574}, {"id": -577}, {"id": -579}, {"id": -581}, {"id": -583}, {"id": -585}, {"id": -587}, {"id": -589}, {"id": -591}, {"id": -593}, {"id": -595}, {"id": -597}, {"id": -599}, {"id": -601}, {"id": -603}, {"id": -605}, {"id": -607}, {"id": -609}, {"id": -610}, {"id": -611}, {"id": -612}, {"id": -617}, {"id": -618}, {"id": -619}, {"id": -620}, {"id": -625}, {"id": -626}, {"id": -627}, {"id": -628}, {"id": -633}, {"id": -634}, {"id": -635}, {"id": -636}, {"id": -641}, {"id": -643}, {"id": -645}, {"id": -647}, {"id": -649}, {"id": -651}, {"id": -653}, {"id": -655}, {"id": -657}, {"id": -659}, {"id": -661}, {"id": -663}, {"id": -665}, {"id": -667}, {"id": -669}, {"id": -671}, {"id": -673}, {"id": -674}, {"id": -677}, {"id": -678}, {"id": -681}, {"id": -682}, {"id": -685}, {"id": -686}, {"id": -689}, {"id": -690}, {"id": -693}, {"id": -694}, {"id": -697}, {"id": -698}, {"id": -701}, {"id": -702}, {"id": -705}, {"id": -707}, {"id": -709}, {"id": -711}, {"id": -713}, {"id": -715}, {"id": -717}, {"id": -719}, {"id": -721}, {"id": -723}, {"id": -725}, {"id": -727}, {"id": -729}, {"id": -731}, {"id": -733}, {"id": -735}, {"id": -737}, {"id": -738}, {"id": -739}, {"id": -740}, {"id": -741}, {"id": -742}, {"id": -743}, {"id": -744}, {"id": -753}, {"id": -754}, {"id": -755}, {"id": -756}, {"id": -757}, {"id": -758}, {"id": -759}, {"id": -760}, {"id": -769}, {"id": -771}, {"id": -773}, {"id": -775}, {"id": -777}, {"id": -779}, {"id": -781}, {"id": -783}, {"id": -785}, {"id": -787}, {"id": -789}, {"id": -791}, {"id": -793}, {"id": -795}, {"id": -797}, {"id": -799}, {"id": -801}, {"id": -802}, {"id": -805}, {"id": -806}, {"id": -809}, {"id": -810}, {"id": -813}, {"id": -814}, {"id": -817}, {"id": -818}, {"id": -821}, {"id": -822}, {"id": -825}, {"id": -826}, {"id": -829}, {"id": -830}, {"id": -833}, {"id": -835}, {"id": -837}, {"id": -839}, {"id": -841}, {"id": -843}, {"id": -845}, {"id": -847}, {"id": -849}, {"id": -851}, {"id": -853}, {"id": -855}, {"id": -857}, {"id": -859}, {"id": -861}, {"id": -863}, {"id": -865}, {"id": -866}, {"id": -867}, {"id": -868}, {"id": -873}, {"id": -874}, {"id": -875}, {"id": -876}, {"id": -881}, {"id": -882}, {"id": -883}, {"id": -884}, {"id": -889}, {"id": -890}, {"id": -891}, {"id": -892}, {"id": -897}, {"id": -899}, {"id": -901}, {"id": -903}, {"id": -905}, {"id": -907}, {"id": -909}, {"id": -911}, {"id": -913}, {"id": -915}, {"id": -917}, {"id": -919}, {"id": -921}, {"id": -923}, {"id": -925}, {"id": -927}, {"id": -929}, {"id": -930}, {"id": -933}, {"id": -934}, {"id": -937}, {"id": -938}, {"id": -941}, {"id": -942}, {"id": -945}, {"id": -946}, {"id": -949}, {"id": -950}, {"id": -953}, {"id": -954}, {"id": -957}, {"id": -958}, {"id": -961}, {"id": 992}, {"id": 993}, {"id": -963}, {"id": 994}, {"id": 995}, {"id": -965}, {"id": 996}, {"id": 997}, {"id": -967}, {"id": 998}, {"id": 999}, {"id": -969}, {"id": 1000}, {"id": 1001}, {"id": -971}, {"id": 1002}, {"id": 1003}, {"id": -973}, {"id": 1004}, {"id": 1005}, {"id": -975}, {"id": 1006}, {"id": 1007}, {"id": -977}, {"id": 1008}, {"id": 1009}, {"id": -979}, {"id": 1010}, {"id": 1011}, {"id": -981}, {"id": 1012}, {"id": 1013}, {"id": -983}, {"id": 1014}, {"id": 1015}, {"id": -985}, {"id": 1016}, {"id": 1017}, {"id": -987}, {"id": 1018}, {"id": 1019}, {"id": -989}, {"id": 1020}, {"id": 1021}, {"id": -991}, {"id": 1022}, {"id": 1023}], "links": [{"source": 0, "target": -1}, {"source": -1, "target": 1}, {"source": -1, "target": -33}, {"source": -1, "target": -34}, {"source": 2, "target": -3}, {"source": -3, "target": 3}, {"source": -3, "target": -33}, {"source": -3, "target": -34}, {"source": 4, "target": -5}, {"source": -5, "target": 5}, {"source": -5, "target": -37}, {"source": -5, "target": -38}, {"source": 6, "target": -7}, {"source": -7, "target": 7}, {"source": -7, "target": -37}, {"source": -7, "target": -38}, {"source": 8, "target": -9}, {"source": -9, "target": 9}, {"source": -9, "target": -41}, {"source": -9, "target": -42}, {"source": 10, "target": -11}, {"source": -11, "target": 11}, {"source": -11, "target": -41}, {"source": -11, "target": -42}, {"source": 12, "target": -13}, {"source": -13, "target": 13}, {"source": -13, "target": -45}, {"source": -13, "target": -46}, {"source": 14, "target": -15}, {"source": -15, "target": 15}, {"source": -15, "target": -45}, {"source": -15, "target": -46}, {"source": 16, "target": -17}, {"source": -17, "target": 17}, {"source": -17, "target": -49}, {"source": -17, "target": -50}, {"source": 18, "target": -19}, {"source": -19, "target": 19}, {"source": -19, "target": -49}, {"source": -19, "target": -50}, {"source": 20, "target": -21}, {"source": -21, "target": 21}, {"source": -21, "target": -53}, {"source": -21, "target": -54}, {"source": 22, "target": -23}, {"source": -23, "target": 23}, {"source": -23, "target": -53}, {"source": -23, "target": -54}, {"source": 24, "target": -25}, {"source": -25, "target": 25}, {"source": -25, "target": -57}, {"source": -25, "target": -58}, {"source": 26, "target": -27}, {"source": -27, "target": 27}, {"source": -27, "target": -57}, {"source": -27, "target": -58}, {"source": 28, "target": -29}, {"source": -29, "target": 29}, {"source": -29, "target": -61}, {"source": -29, "target": -62}, {"source": 30, "target": -31}, {"source": -31, "target": 31}, {"source": -31, "target": -61}, {"source": -31, "target": -62}, {"source": -33, "target": -65}, {"source": -33, "target": -67}, {"source": -34, "target": -65}, {"source": -34, "target": -67}, {"source": -37, "target": -69}, {"source": -37, "target": -71}, {"source": -38, "target": -69}, {"source": -38, "target": -71}, {"source": -41, "target": -73}, {"source": -41, "target": -75}, {"source": -42, "target": -73}, {"source": -42, "target": -75}, {"source": -45, "target": -77}, {"source": -45, "target": -79}, {"source": -46, "target": -77}, {"source": -46, "target": -79}, {"source": -49, "target": -81}, {"source": -49, "target": -83}, {"source": -50, "target": -81}, {"source": -50, "target": -83}, {"source": -53, "target": -85}, {"source": -53, "target": -87}, {"source": -54, "target": -85}, {"source": -54, "target": -87}, {"source": -57, "target": -89}, {"source": -57, "target": -91}, {"source": -58, "target": -89}, {"source": -58, "target": -91}, {"source": -61, "target": -93}, {"source": -61, "target": -95}, {"source": -62, "target": -93}, {"source": -62, "target": -95}, {"source": -65, "target": -97}, {"source": -65, "target": -98}, {"source": -67, "target": -99}, {"source": -67, "target": -100}, {"source": -69, "target": -97}, {"source": -69, "target": -98}, {"source": -71, "target": -99}, {"source": -71, "target": -100}, {"source": -73, "target": -105}, {"source": -73, "target": -106}, {"source": -75, "target": -107}, {"source": -75, "target": -108}, {"source": -77, "target": -105}, {"source": -77, "target": -106}, {"source": -79, "target": -107}, {"source": -79, "target": -108}, {"source": -81, "target": -113}, {"source": -81, "target": -114}, {"source": -83, "target": -115}, {"source": -83, "target": -116}, {"source": -85, "target": -113}, {"source": -85, "target": -114}, {"source": -87, "target": -115}, {"source": -87, "target": -116}, {"source": -89, "target": -121}, {"source": -89, "target": -122}, {"source": -91, "target": -123}, {"source": -91, "target": -124}, {"source": -93, "target": -121}, {"source": -93, "target": -122}, {"source": -95, "target": -123}, {"source": -95, "target": -124}, {"source": -97, "target": -129}, {"source": -97, "target": -133}, {"source": -98, "target": -129}, {"source": -98, "target": -133}, {"source": -99, "target": -131}, {"source": -99, "target": -135}, {"source": -100, "target": -131}, {"source": -100, "target": -135}, {"source": -105, "target": -137}, {"source": -105, "target": -141}, {"source": -106, "target": -137}, {"source": -106, "target": -141}, {"source": -107, "target": -139}, {"source": -107, "target": -143}, {"source": -108, "target": -139}, {"source": -108, "target": -143}, {"source": -113, "target": -145}, {"source": -113, "target": -149}, {"source": -114, "target": -145}, {"source": -114, "target": -149}, {"source": -115, "target": -147}, {"source": -115, "target": -151}, {"source": -116, "target": -147}, {"source": -116, "target": -151}, {"source": -121, "target": -153}, {"source": -121, "target": -157}, {"source": -122, "target": -153}, {"source": -122, "target": -157}, {"source": -123, "target": -155}, {"source": -123, "target": -159}, {"source": -124, "target": -155}, {"source": -124, "target": -159}, {"source": -129, "target": -161}, {"source": -129, "target": -162}, {"source": -131, "target": -161}, {"source": -131, "target": -162}, {"source": -133, "target": -165}, {"source": -133, "target": -166}, {"source": -135, "target": -165}, {"source": -135, "target": -166}, {"source": -137, "target": -169}, {"source": -137, "target": -170}, {"source": -139, "target": -169}, {"source": -139, "target": -170}, {"source": -141, "target": -173}, {"source": -141, "target": -174}, {"source": -143, "target": -173}, {"source": -143, "target": -174}, {"source": -145, "target": -177}, {"source": -145, "target": -178}, {"source": -147, "target": -177}, {"source": -147, "target": -178}, {"source": -149, "target": -181}, {"source": -149, "target": -182}, {"source": -151, "target": -181}, {"source": -151, "target": -182}, {"source": -153, "target": -185}, {"source": -153, "target": -186}, {"source": -155, "target": -185}, {"source": -155, "target": -186}, {"source": -157, "target": -189}, {"source": -157, "target": -190}, {"source": -159, "target": -189}, {"source": -159, "target": -190}, {"source": -161, "target": -193}, {"source": -161, "target": -195}, {"source": -162, "target": -193}, {"source": -162, "target": -195}, {"source": -165, "target": -197}, {"source": -165, "target": -199}, {"source": -166, "target": -197}, {"source": -166, "target": -199}, {"source": -169, "target": -201}, {"source": -169, "target": -203}, {"source": -170, "target": -201}, {"source": -170, "target": -203}, {"source": -173, "target": -205}, {"source": -173, "target": -207}, {"source": -174, "target": -205}, {"source": -174, "target": -207}, {"source": -177, "target": -209}, {"source": -177, "target": -211}, {"source": -178, "target": -209}, {"source": -178, "target": -211}, {"source": -181, "target": -213}, {"source": -181, "target": -215}, {"source": -182, "target": -213}, {"source": -182, "target": -215}, {"source": -185, "target": -217}, {"source": -185, "target": -219}, {"source": -186, "target": -217}, {"source": -186, "target": -219}, {"source": -189, "target": -221}, {"source": -189, "target": -223}, {"source": -190, "target": -221}, {"source": -190, "target": -223}, {"source": -193, "target": -225}, {"source": -193, "target": -226}, {"source": -195, "target": -227}, {"source": -195, "target": -228}, {"source": -197, "target": -229}, {"source": -197, "target": -230}, {"source": -199, "target": -231}, {"source": -199, "target": -232}, {"source": -201, "target": -225}, {"source": -201, "target": -226}, {"source": -203, "target": -227}, {"source": -203, "target": -228}, {"source": -205, "target": -229}, {"source": -205, "target": -230}, {"source": -207, "target": -231}, {"source": -207, "target": -232}, {"source": -209, "target": -241}, {"source": -209, "target": -242}, {"source": -211, "target": -243}, {"source": -211, "target": -244}, {"source": -213, "target": -245}, {"source": -213, "target": -246}, {"source": -215, "target": -247}, {"source": -215, "target": -248}, {"source": -217, "target": -241}, {"source": -217, "target": -242}, {"source": -219, "target": -243}, {"source": -219, "target": -244}, {"source": -221, "target": -245}, {"source": -221, "target": -246}, {"source": -223, "target": -247}, {"source": -223, "target": -248}, {"source": -225, "target": -257}, {"source": -225, "target": -265}, {"source": -226, "target": -257}, {"source": -226, "target": -265}, {"source": -227, "target": -259}, {"source": -227, "target": -267}, {"source": -228, "target": -259}, {"source": -228, "target": -267}, {"source": -229, "target": -261}, {"source": -229, "target": -269}, {"source": -230, "target": -261}, {"source": -230, "target": -269}, {"source": -231, "target": -263}, {"source": -231, "target": -271}, {"source": -232, "target": -263}, {"source": -232, "target": -271}, {"source": -241, "target": -273}, {"source": -241, "target": -281}, {"source": -242, "target": -273}, {"source": -242, "target": -281}, {"source": -243, "target": -275}, {"source": -243, "target": -283}, {"source": -244, "target": -275}, {"source": -244, "target": -283}, {"source": -245, "target": -277}, {"source": -245, "target": -285}, {"source": -246, "target": -277}, {"source": -246, "target": -285}, {"source": -247, "target": -279}, {"source": -247, "target": -287}, {"source": -248, "target": -279}, {"source": -248, "target": -287}, {"source": -257, "target": -289}, {"source": -257, "target": -290}, {"source": -259, "target": -289}, {"source": -259, "target": -290}, {"source": -261, "target": -293}, {"source": -261, "target": -294}, {"source": -263, "target": -293}, {"source": -263, "target": -294}, {"source": -265, "target": -297}, {"source": -265, "target": -298}, {"source": -267, "target": -297}, {"source": -267, "target": -298}, {"source": -269, "target": -301}, {"source": -269, "target": -302}, {"source": -271, "target": -301}, {"source": -271, "target": -302}, {"source": -273, "target": -305}, {"source": -273, "target": -306}, {"source": -275, "target": -305}, {"source": -275, "target": -306}, {"source": -277, "target": -309}, {"source": -277, "target": -310}, {"source": -279, "target": -309}, {"source": -279, "target": -310}, {"source": -281, "target": -313}, {"source": -281, "target": -314}, {"source": -283, "target": -313}, {"source": -283, "target": -314}, {"source": -285, "target": -317}, {"source": -285, "target": -318}, {"source": -287, "target": -317}, {"source": -287, "target": -318}, {"source": -289, "target": -321}, {"source": -289, "target": -323}, {"source": -290, "target": -321}, {"source": -290, "target": -323}, {"source": -293, "target": -325}, {"source": -293, "target": -327}, {"source": -294, "target": -325}, {"source": -294, "target": -327}, {"source": -297, "target": -329}, {"source": -297, "target": -331}, {"source": -298, "target": -329}, {"source": -298, "target": -331}, {"source": -301, "target": -333}, {"source": -301, "target": -335}, {"source": -302, "target": -333}, {"source": -302, "target": -335}, {"source": -305, "target": -337}, {"source": -305, "target": -339}, {"source": -306, "target": -337}, {"source": -306, "target": -339}, {"source": -309, "target": -341}, {"source": -309, "target": -343}, {"source": -310, "target": -341}, {"source": -310, "target": -343}, {"source": -313, "target": -345}, {"source": -313, "target": -347}, {"source": -314, "target": -345}, {"source": -314, "target": -347}, {"source": -317, "target": -349}, {"source": -317, "target": -351}, {"source": -318, "target": -349}, {"source": -318, "target": -351}, {"source": -321, "target": -353}, {"source": -321, "target": -354}, {"source": -323, "target": -355}, {"source": -323, "target": -356}, {"source": -325, "target": -353}, {"source": -325, "target": -354}, {"source": -327, "target": -355}, {"source": -327, "target": -356}, {"source": -329, "target": -361}, {"source": -329, "target": -362}, {"source": -331, "target": -363}, {"source": -331, "target": -364}, {"source": -333, "target": -361}, {"source": -333, "target": -362}, {"source": -335, "target": -363}, {"source": -335, "target": -364}, {"source": -337, "target": -369}, {"source": -337, "target": -370}, {"source": -339, "target": -371}, {"source": -339, "target": -372}, {"source": -341, "target": -369}, {"source": -341, "target": -370}, {"source": -343, "target": -371}, {"source": -343, "target": -372}, {"source": -345, "target": -377}, {"source": -345, "target": -378}, {"source": -347, "target": -379}, {"source": -347, "target": -380}, {"source": -349, "target": -377}, {"source": -349, "target": -378}, {"source": -351, "target": -379}, {"source": -351, "target": -380}, {"source": -353, "target": -385}, {"source": -353, "target": -389}, {"source": -354, "target": -385}, {"source": -354, "target": -389}, {"source": -355, "target": -387}, {"source": -355, "target": -391}, {"source": -356, "target": -387}, {"source": -356, "target": -391}, {"source": -361, "target": -393}, {"source": -361, "target": -397}, {"source": -362, "target": -393}, {"source": -362, "target": -397}, {"source": -363, "target": -395}, {"source": -363, "target": -399}, {"source": -364, "target": -395}, {"source": -364, "target": -399}, {"source": -369, "target": -401}, {"source": -369, "target": -405}, {"source": -370, "target": -401}, {"source": -370, "target": -405}, {"source": -371, "target": -403}, {"source": -371, "target": -407}, {"source": -372, "target": -403}, {"source": -372, "target": -407}, {"source": -377, "target": -409}, {"source": -377, "target": -413}, {"source": -378, "target": -409}, {"source": -378, "target": -413}, {"source": -379, "target": -411}, {"source": -379, "target": -415}, {"source": -380, "target": -411}, {"source": -380, "target": -415}, {"source": -385, "target": -417}, {"source": -385, "target": -418}, {"source": -387, "target": -417}, {"source": -387, "target": -418}, {"source": -389, "target": -421}, {"source": -389, "target": -422}, {"source": -391, "target": -421}, {"source": -391, "target": -422}, {"source": -393, "target": -425}, {"source": -393, "target": -426}, {"source": -395, "target": -425}, {"source": -395, "target": -426}, {"source": -397, "target": -429}, {"source": -397, "target": -430}, {"source": -399, "target": -429}, {"source": -399, "target": -430}, {"source": -401, "target": -433}, {"source": -401, "target": -434}, {"source": -403, "target": -433}, {"source": -403, "target": -434}, {"source": -405, "target": -437}, {"source": -405, "target": -438}, {"source": -407, "target": -437}, {"source": -407, "target": -438}, {"source": -409, "target": -441}, {"source": -409, "target": -442}, {"source": -411, "target": -441}, {"source": -411, "target": -442}, {"source": -413, "target": -445}, {"source": -413, "target": -446}, {"source": -415, "target": -445}, {"source": -415, "target": -446}, {"source": -417, "target": -449}, {"source": -417, "target": -451}, {"source": -418, "target": -449}, {"source": -418, "target": -451}, {"source": -421, "target": -453}, {"source": -421, "target": -455}, {"source": -422, "target": -453}, {"source": -422, "target": -455}, {"source": -425, "target": -457}, {"source": -425, "target": -459}, {"source": -426, "target": -457}, {"source": -426, "target": -459}, {"source": -429, "target": -461}, {"source": -429, "target": -463}, {"source": -430, "target": -461}, {"source": -430, "target": -463}, {"source": -433, "target": -465}, {"source": -433, "target": -467}, {"source": -434, "target": -465}, {"source": -434, "target": -467}, {"source": -437, "target": -469}, {"source": -437, "target": -471}, {"source": -438, "target": -469}, {"source": -438, "target": -471}, {"source": -441, "target": -473}, {"source": -441, "target": -475}, {"source": -442, "target": -473}, {"source": -442, "target": -475}, {"source": -445, "target": -477}, {"source": -445, "target": -479}, {"source": -446, "target": -477}, {"source": -446, "target": -479}, {"source": -449, "target": -481}, {"source": -449, "target": -482}, {"source": -451, "target": -483}, {"source": -451, "target": -484}, {"source": -453, "target": -485}, {"source": -453, "target": -486}, {"source": -455, "target": -487}, {"source": -455, "target": -488}, {"source": -457, "target": -489}, {"source": -457, "target": -490}, {"source": -459, "target": -491}, {"source": -459, "target": -492}, {"source": -461, "target": -493}, {"source": -461, "target": -494}, {"source": -463, "target": -495}, {"source": -463, "target": -496}, {"source": -465, "target": -481}, {"source": -465, "target": -482}, {"source": -467, "target": -483}, {"source": -467, "target": -484}, {"source": -469, "target": -485}, {"source": -469, "target": -486}, {"source": -471, "target": -487}, {"source": -471, "target": -488}, {"source": -473, "target": -489}, {"source": -473, "target": -490}, {"source": -475, "target": -491}, {"source": -475, "target": -492}, {"source": -477, "target": -493}, {"source": -477, "target": -494}, {"source": -479, "target": -495}, {"source": -479, "target": -496}, {"source": -481, "target": -513}, {"source": -481, "target": -529}, {"source": -482, "target": -513}, {"source": -482, "target": -529}, {"source": -483, "target": -515}, {"source": -483, "target": -531}, {"source": -484, "target": -515}, {"source": -484, "target": -531}, {"source": -485, "target": -517}, {"source": -485, "target": -533}, {"source": -486, "target": -517}, {"source": -486, "target": -533}, {"source": -487, "target": -519}, {"source": -487, "target": -535}, {"source": -488, "target": -519}, {"source": -488, "target": -535}, {"source": -489, "target": -521}, {"source": -489, "target": -537}, {"source": -490, "target": -521}, {"source": -490, "target": -537}, {"source": -491, "target": -523}, {"source": -491, "target": -539}, {"source": -492, "target": -523}, {"source": -492, "target": -539}, {"source": -493, "target": -525}, {"source": -493, "target": -541}, {"source": -494, "target": -525}, {"source": -494, "target": -541}, {"source": -495, "target": -527}, {"source": -495, "target": -543}, {"source": -496, "target": -527}, {"source": -496, "target": -543}, {"source": -513, "target": -545}, {"source": -513, "target": -546}, {"source": -515, "target": -545}, {"source": -515, "target": -546}, {"source": -517, "target": -549}, {"source": -517, "target": -550}, {"source": -519, "target": -549}, {"source": -519, "target": -550}, {"source": -521, "target": -553}, {"source": -521, "target": -554}, {"source": -523, "target": -553}, {"source": -523, "target": -554}, {"source": -525, "target": -557}, {"source": -525, "target": -558}, {"source": -527, "target": -557}, {"source": -527, "target": -558}, {"source": -529, "target": -561}, {"source": -529, "target": -562}, {"source": -531, "target": -561}, {"source": -531, "target": -562}, {"source": -533, "target": -565}, {"source": -533, "target": -566}, {"source": -535, "target": -565}, {"source": -535, "target": -566}, {"source": -537, "target": -569}, {"source": -537, "target": -570}, {"source": -539, "target": -569}, {"source": -539, "target": -570}, {"source": -541, "target": -573}, {"source": -541, "target": -574}, {"source": -543, "target": -573}, {"source": -543, "target": -574}, {"source": -545, "target": -577}, {"source": -545, "target": -579}, {"source": -546, "target": -577}, {"source": -546, "target": -579}, {"source": -549, "target": -581}, {"source": -549, "target": -583}, {"source": -550, "target": -581}, {"source": -550, "target": -583}, {"source": -553, "target": -585}, {"source": -553, "target": -587}, {"source": -554, "target": -585}, {"source": -554, "target": -587}, {"source": -557, "target": -589}, {"source": -557, "target": -591}, {"source": -558, "target": -589}, {"source": -558, "target": -591}, {"source": -561, "target": -593}, {"source": -561, "target": -595}, {"source": -562, "target": -593}, {"source": -562, "target": -595}, {"source": -565, "target": -597}, {"source": -565, "target": -599}, {"source": -566, "target": -597}, {"source": -566, "target": -599}, {"source": -569, "target": -601}, {"source": -569, "target": -603}, {"source": -570, "target": -601}, {"source": -570, "target": -603}, {"source": -573, "target": -605}, {"source": -573, "target": -607}, {"source": -574, "target": -605}, {"source": -574, "target": -607}, {"source": -577, "target": -609}, {"source": -577, "target": -610}, {"source": -579, "target": -611}, {"source": -579, "target": -612}, {"source": -581, "target": -609}, {"source": -581, "target": -610}, {"source": -583, "target": -611}, {"source": -583, "target": -612}, {"source": -585, "target": -617}, {"source": -585, "target": -618}, {"source": -587, "target": -619}, {"source": -587, "target": -620}, {"source": -589, "target": -617}, {"source": -589, "target": -618}, {"source": -591, "target": -619}, {"source": -591, "target": -620}, {"source": -593, "target": -625}, {"source": -593, "target": -626}, {"source": -595, "target": -627}, {"source": -595, "target": -628}, {"source": -597, "target": -625}, {"source": -597, "target": -626}, {"source": -599, "target": -627}, {"source": -599, "target": -628}, {"source": -601, "target": -633}, {"source": -601, "target": -634}, {"source": -603, "target": -635}, {"source": -603, "target": -636}, {"source": -605, "target": -633}, {"source": -605, "target": -634}, {"source": -607, "target": -635}, {"source": -607, "target": -636}, {"source": -609, "target": -641}, {"source": -609, "target": -645}, {"source": -610, "target": -641}, {"source": -610, "target": -645}, {"source": -611, "target": -643}, {"source": -611, "target": -647}, {"source": -612, "target": -643}, {"source": -612, "target": -647}, {"source": -617, "target": -649}, {"source": -617, "target": -653}, {"source": -618, "target": -649}, {"source": -618, "target": -653}, {"source": -619, "target": -651}, {"source": -619, "target": -655}, {"source": -620, "target": -651}, {"source": -620, "target": -655}, {"source": -625, "target": -657}, {"source": -625, "target": -661}, {"source": -626, "target": -657}, {"source": -626, "target": -661}, {"source": -627, "target": -659}, {"source": -627, "target": -663}, {"source": -628, "target": -659}, {"source": -628, "target": -663}, {"source": -633, "target": -665}, {"source": -633, "target": -669}, {"source": -634, "target": -665}, {"source": -634, "target": -669}, {"source": -635, "target": -667}, {"source": -635, "target": -671}, {"source": -636, "target": -667}, {"source": -636, "target": -671}, {"source": -641, "target": -673}, {"source": -641, "target": -674}, {"source": -643, "target": -673}, {"source": -643, "target": -674}, {"source": -645, "target": -677}, {"source": -645, "target": -678}, {"source": -647, "target": -677}, {"source": -647, "target": -678}, {"source": -649, "target": -681}, {"source": -649, "target": -682}, {"source": -651, "target": -681}, {"source": -651, "target": -682}, {"source": -653, "target": -685}, {"source": -653, "target": -686}, {"source": -655, "target": -685}, {"source": -655, "target": -686}, {"source": -657, "target": -689}, {"source": -657, "target": -690}, {"source": -659, "target": -689}, {"source": -659, "target": -690}, {"source": -661, "target": -693}, {"source": -661, "target": -694}, {"source": -663, "target": -693}, {"source": -663, "target": -694}, {"source": -665, "target": -697}, {"source": -665, "target": -698}, {"source": -667, "target": -697}, {"source": -667, "target": -698}, {"source": -669, "target": -701}, {"source": -669, "target": -702}, {"source": -671, "target": -701}, {"source": -671, "target": -702}, {"source": -673, "target": -705}, {"source": -673, "target": -707}, {"source": -674, "target": -705}, {"source": -674, "target": -707}, {"source": -677, "target": -709}, {"source": -677, "target": -711}, {"source": -678, "target": -709}, {"source": -678, "target": -711}, {"source": -681, "target": -713}, {"source": -681, "target": -715}, {"source": -682, "target": -713}, {"source": -682, "target": -715}, {"source": -685, "target": -717}, {"source": -685, "target": -719}, {"source": -686, "target": -717}, {"source": -686, "target": -719}, {"source": -689, "target": -721}, {"source": -689, "target": -723}, {"source": -690, "target": -721}, {"source": -690, "target": -723}, {"source": -693, "target": -725}, {"source": -693, "target": -727}, {"source": -694, "target": -725}, {"source": -694, "target": -727}, {"source": -697, "target": -729}, {"source": -697, "target": -731}, {"source": -698, "target": -729}, {"source": -698, "target": -731}, {"source": -701, "target": -733}, {"source": -701, "target": -735}, {"source": -702, "target": -733}, {"source": -702, "target": -735}, {"source": -705, "target": -737}, {"source": -705, "target": -738}, {"source": -707, "target": -739}, {"source": -707, "target": -740}, {"source": -709, "target": -741}, {"source": -709, "target": -742}, {"source": -711, "target": -743}, {"source": -711, "target": -744}, {"source": -713, "target": -737}, {"source": -713, "target": -738}, {"source": -715, "target": -739}, {"source": -715, "target": -740}, {"source": -717, "target": -741}, {"source": -717, "target": -742}, {"source": -719, "target": -743}, {"source": -719, "target": -744}, {"source": -721, "target": -753}, {"source": -721, "target": -754}, {"source": -723, "target": -755}, {"source": -723, "target": -756}, {"source": -725, "target": -757}, {"source": -725, "target": -758}, {"source": -727, "target": -759}, {"source": -727, "target": -760}, {"source": -729, "target": -753}, {"source": -729, "target": -754}, {"source": -731, "target": -755}, {"source": -731, "target": -756}, {"source": -733, "target": -757}, {"source": -733, "target": -758}, {"source": -735, "target": -759}, {"source": -735, "target": -760}, {"source": -737, "target": -769}, {"source": -737, "target": -777}, {"source": -738, "target": -769}, {"source": -738, "target": -777}, {"source": -739, "target": -771}, {"source": -739, "target": -779}, {"source": -740, "target": -771}, {"source": -740, "target": -779}, {"source": -741, "target": -773}, {"source": -741, "target": -781}, {"source": -742, "target": -773}, {"source": -742, "target": -781}, {"source": -743, "target": -775}, {"source": -743, "target": -783}, {"source": -744, "target": -775}, {"source": -744, "target": -783}, {"source": -753, "target": -785}, {"source": -753, "target": -793}, {"source": -754, "target": -785}, {"source": -754, "target": -793}, {"source": -755, "target": -787}, {"source": -755, "target": -795}, {"source": -756, "target": -787}, {"source": -756, "target": -795}, {"source": -757, "target": -789}, {"source": -757, "target": -797}, {"source": -758, "target": -789}, {"source": -758, "target": -797}, {"source": -759, "target": -791}, {"source": -759, "target": -799}, {"source": -760, "target": -791}, {"source": -760, "target": -799}, {"source": -769, "target": -801}, {"source": -769, "target": -802}, {"source": -771, "target": -801}, {"source": -771, "target": -802}, {"source": -773, "target": -805}, {"source": -773, "target": -806}, {"source": -775, "target": -805}, {"source": -775, "target": -806}, {"source": -777, "target": -809}, {"source": -777, "target": -810}, {"source": -779, "target": -809}, {"source": -779, "target": -810}, {"source": -781, "target": -813}, {"source": -781, "target": -814}, {"source": -783, "target": -813}, {"source": -783, "target": -814}, {"source": -785, "target": -817}, {"source": -785, "target": -818}, {"source": -787, "target": -817}, {"source": -787, "target": -818}, {"source": -789, "target": -821}, {"source": -789, "target": -822}, {"source": -791, "target": -821}, {"source": -791, "target": -822}, {"source": -793, "target": -825}, {"source": -793, "target": -826}, {"source": -795, "target": -825}, {"source": -795, "target": -826}, {"source": -797, "target": -829}, {"source": -797, "target": -830}, {"source": -799, "target": -829}, {"source": -799, "target": -830}, {"source": -801, "target": -833}, {"source": -801, "target": -835}, {"source": -802, "target": -833}, {"source": -802, "target": -835}, {"source": -805, "target": -837}, {"source": -805, "target": -839}, {"source": -806, "target": -837}, {"source": -806, "target": -839}, {"source": -809, "target": -841}, {"source": -809, "target": -843}, {"source": -810, "target": -841}, {"source": -810, "target": -843}, {"source": -813, "target": -845}, {"source": -813, "target": -847}, {"source": -814, "target": -845}, {"source": -814, "target": -847}, {"source": -817, "target": -849}, {"source": -817, "target": -851}, {"source": -818, "target": -849}, {"source": -818, "target": -851}, {"source": -821, "target": -853}, {"source": -821, "target": -855}, {"source": -822, "target": -853}, {"source": -822, "target": -855}, {"source": -825, "target": -857}, {"source": -825, "target": -859}, {"source": -826, "target": -857}, {"source": -826, "target": -859}, {"source": -829, "target": -861}, {"source": -829, "target": -863}, {"source": -830, "target": -861}, {"source": -830, "target": -863}, {"source": -833, "target": -865}, {"source": -833, "target": -866}, {"source": -835, "target": -867}, {"source": -835, "target": -868}, {"source": -837, "target": -865}, {"source": -837, "target": -866}, {"source": -839, "target": -867}, {"source": -839, "target": -868}, {"source": -841, "target": -873}, {"source": -841, "target": -874}, {"source": -843, "target": -875}, {"source": -843, "target": -876}, {"source": -845, "target": -873}, {"source": -845, "target": -874}, {"source": -847, "target": -875}, {"source": -847, "target": -876}, {"source": -849, "target": -881}, {"source": -849, "target": -882}, {"source": -851, "target": -883}, {"source": -851, "target": -884}, {"source": -853, "target": -881}, {"source": -853, "target": -882}, {"source": -855, "target": -883}, {"source": -855, "target": -884}, {"source": -857, "target": -889}, {"source": -857, "target": -890}, {"source": -859, "target": -891}, {"source": -859, "target": -892}, {"source": -861, "target": -889}, {"source": -861, "target": -890}, {"source": -863, "target": -891}, {"source": -863, "target": -892}, {"source": -865, "target": -897}, {"source": -865, "target": -901}, {"source": -866, "target": -897}, {"source": -866, "target": -901}, {"source": -867, "target": -899}, {"source": -867, "target": -903}, {"source": -868, "target": -899}, {"source": -868, "target": -903}, {"source": -873, "target": -905}, {"source": -873, "target": -909}, {"source": -874, "target": -905}, {"source": -874, "target": -909}, {"source": -875, "target": -907}, {"source": -875, "target": -911}, {"source": -876, "target": -907}, {"source": -876, "target": -911}, {"source": -881, "target": -913}, {"source": -881, "target": -917}, {"source": -882, "target": -913}, {"source": -882, "target": -917}, {"source": -883, "target": -915}, {"source": -883, "target": -919}, {"source": -884, "target": -915}, {"source": -884, "target": -919}, {"source": -889, "target": -921}, {"source": -889, "target": -925}, {"source": -890, "target": -921}, {"source": -890, "target": -925}, {"source": -891, "target": -923}, {"source": -891, "target": -927}, {"source": -892, "target": -923}, {"source": -892, "target": -927}, {"source": -897, "target": -929}, {"source": -897, "target": -930}, {"source": -899, "target": -929}, {"source": -899, "target": -930}, {"source": -901, "target": -933}, {"source": -901, "target": -934}, {"source": -903, "target": -933}, {"source": -903, "target": -934}, {"source": -905, "target": -937}, {"source": -905, "target": -938}, {"source": -907, "target": -937}, {"source": -907, "target": -938}, {"source": -909, "target": -941}, {"source": -909, "target": -942}, {"source": -911, "target": -941}, {"source": -911, "target": -942}, {"source": -913, "target": -945}, {"source": -913, "target": -946}, {"source": -915, "target": -945}, {"source": -915, "target": -946}, {"source": -917, "target": -949}, {"source": -917, "target": -950}, {"source": -919, "target": -949}, {"source": -919, "target": -950}, {"source": -921, "target": -953}, {"source": -921, "target": -954}, {"source": -923, "target": -953}, {"source": -923, "target": -954}, {"source": -925, "target": -957}, {"source": -925, "target": -958}, {"source": -927, "target": -957}, {"source": -927, "target": -958}, {"source": -929, "target": -961}, {"source": -929, "target": -963}, {"source": -930, "target": -961}, {"source": -930, "target": -963}, {"source": -933, "target": -965}, {"source": -933, "target": -967}, {"source": -934, "target": -965}, {"source": -934, "target": -967}, {"source": -937, "target": -969}, {"source": -937, "target": -971}, {"source": -938, "target": -969}, {"source": -938, "target": -971}, {"source": -941, "target": -973}, {"source": -941, "target": -975}, {"source": -942, "target": -973}, {"source": -942, "target": -975}, {"source": -945, "target": -977}, {"source": -945, "target": -979}, {"source": -946, "target": -977}, {"source": -946, "target": -979}, {"source": -949, "target": -981}, {"source": -949, "target": -983}, {"source": -950, "target": -981}, {"source": -950, "target": -983}, {"source": -953, "target": -985}, {"source": -953, "target": -987}, {"source": -954, "target": -985}, {"source": -954, "target": -987}, {"source": -957, "target": -989}, {"source": -957, "target": -991}, {"source": -958, "target": -989}, {"source": -958, "target": -991}, {"source": -961, "target": 992}, {"source": -961, "target": 993}, {"source": -963, "target": 994}, {"source": -963, "target": 995}, {"source": -965, "target": 996}, {"source": -965, "target": 997}, {"source": -967, "target": 998}, {"source": -967, "target": 999}, {"source": -969, "target": 1000}, {"source": -969, "target": 1001}, {"source": -971, "target": 1002}, {"source": -971, "target": 1003}, {"source": -973, "target": 1004}, {"source": -973, "target": 1005}, {"source": -975, "target": 1006}, {"source": -975, "target": 1007}, {"source": -977, "target": 1008}, {"source": -977, "target": 1009}, {"source": -979, "target": 1010}, {"source": -979, "target": 1011}, {"source": -981, "target": 1012}, {"source": -981, "target": 1013}, {"source": -983, "target": 1014}, {"source": -983, "target": 1015}, {"source": -985, "target": 1016}, {"source": -985, "target": 1017}, {"source": -987, "target": 1018}, {"source": -987, "target": 1019}, {"source": -989, "target": 1020}, {"source": -989, "target": 1021}, {"source": -991, "target": 1022}, {"source": -991, "target": 1023}]}